crlite_python-0.2.4.dist-info/METADATA
crlite_python-0.2.4.dist-info/WHEEL
crlite_python-0.2.4.dist-info/licenses/LICENSE.txt
crlite_python.libs/libgcc_s-b5472b99.so.1
crlite_python/_internal.pyi
crlite_python/exceptions.py
crlite_python/crlite.py
crlite_python/__init__.py
crlite_python/_internal.cpython-312-i386-linux-musl.so
crlite_python-0.2.4.dist-info/RECORD
