Metadata-Version: 2.4
Name: crlite-python
Version: 0.2.4
Classifier: Programming Language :: Rust
Classifier: Programming Language :: Python :: Implementation :: CPython
Classifier: Programming Language :: Python :: Implementation :: PyPy
Requires-Dist: cryptography>=44.0.2
Requires-Dist: requests>=2.32.3
Requires-Dist: pytest ; extra == 'tests'
Provides-Extra: tests
License-File: LICENSE.txt
Author-email: Teja Juluru <44445080+hawkeyes1094@users.noreply.github.com>
Requires-Python: >=3.8
Project-URL: repository, https://github.com/hawkeyes1094/crlite-python
